{
  "extension.displayName": "Saropa Lints",
  "extension.description": "2100+ Dart/Flutter قوانین lint با تجزیه و تحلیل بصری، به علاوه بسته Vibrancy برای امتیاز دهی سلامت وابستگی، اسکن آسیب پذیری و برنامه ریزی ارتقاء.",
  "views.container.title": "Saropa Lints",
  "views.banner.name": "Saropa Lints",
  "views.editorDashboards.name": "داشبورد های ویرایشگر، دش بوردهای مدیر",
  "views.actions.name": "اقدامات اقداماتی که انجام می شود",
  "views.status.name": "وضعیت Status موقعیت وضعیت",
  "views.settings.name": "تنظیمات Settings تنظیمات",
  "views.help.name": "کمک به یاری کردن",
  "viewsWelcome.banner.contents": "**Saropa Lints** 2100+ Dart و Flutter قوانین لنت برای امنیت، دسترسی پذیری و عملکرد.\n\nنیاز به یک پروژه Dart یا Flutter دارد.\n\nبرای شروع یک پوشه حاوی `pubspec.yaml̅ را باز کنید.\n\n[بیشتر در اینستاگرام بخوانید]https://pub.dev/packages/saropa_lints)\n[بررسي تمام فرمان ها] (کمانده:saropaLints.showCommandCatalog)\n[در مورد Saropa Lints]{کمانده:saropaLints.showAbout}\n[آغاز کردن]{کمانده:saropaLints.openWalkthrough}",
  "command.enable.title": "Saropa Lints: تنظیم پروژه (pubspec + config)",
  "command.disable.title": "Saropa Lints: خاموش کردن ادغام Lint",
  "command.runAnalysis.title": "Saropa Lints: اجرای تحلیل",
  "command.verifyPlugin.title": "Saropa Lints: بررسی اینکه پلاگین در حال اجرا است (بررسی زنده بودن)",
  "command.initializeConfig.title": "Saropa Lints: گزینه های تحلیل را آغاز کنید / به روزرسانی کنید.",
  "command.createBaseline.title": "Saropa Lints: _PH0_: = PH0__::: -پای ایجاد خط پایه (کاهش نقض های موجود)",
  "command.checkForUpdatesNow.title": "Saropa Lints: _PH0_: = PH0__::: -پای چک کردن به روز رسانی های بسته در حال حاضر",
  "command.enableRulePack.title": "Saropa Lints: _PH0_: = PH0__::: -پای فعال کردن Rule Pack",
  "command.emitCompositePluginScaffold.title": "Saropa Lints: ایجاد پلاگین Composite Analyzer (پنجره)",
  "command.openConfig.title": "Saropa Lints: گزینه های تجزیه و تحلیل باز",
  "command.openPubspec.title": "Saropa Lints: باز کردن pubspec.yaml",
  "command.toggleRunAnalysisAfterConfigChange.title": "Saropa Lints: Toggle Run Analysis After Config Change (تحلیل اجرا و تغییر پس از پیکربندی) را در اختیار بگذارید.",
  "command.toggleRunAnalysisAfterDependencyChange.title": "Saropa Lints: Toggle Run Analysis After Dependency Change (تحلیل اجرای تغییر پس از وابستگی)",
  "command.pickUiLanguage.title": "Saropa Lints: Language / Langue / Sprache / 言語 / 语言",
  "command.openConfigDashboard.title": "Saropa Lints: _PH0_: = PH0__::: -پای مدیریت Rule Packs بسته های قاعده",
  "command.openPackageVibrancy.title": "Saropa Lints: باز کردن پویایی بسته",
  "command.openProjectVibrancyReport.title": "Saropa Lints: باز کردن داشبورد سلامت کد",
  "command.openProjectVibrancySettings.title": "Saropa Lints: کد باز تنظیمات بهداشتی",
  "command.crossFile.unusedFiles.title": "Saropa Lints: Cross-File  ⁇  فایل های استفاده نشده را پیدا کنید",
  "command.crossFile.circularDeps.title": "Saropa Lints: Cross-File  ⁇  تشخیص وابستگی های دایره ای",
  "command.crossFile.importStats.title": "Saropa Lints: Cross-File  ⁇  آمار واردات را نشان می دهد",
  "command.crossFile.featureDeps.title": "Saropa Lints: Cross-File  ⁇  نشان دادن وابستگی های ویژگی",
  "command.crossFile.unusedSymbols.title": "Saropa Lints: Cross-File  ⁇  پیدا کردن نمادهای استفاده نشده",
  "command.crossFile.deadImports.title": "Saropa Lints: Cross-File  ⁇  پیدا کردن واردات مرده",
  "command.crossFile.unusedL10n.title": "Saropa Lints: کراس فایل  ⁇  پیدا کردن کلید های غیر استفاده شده l10n",
  "command.crossFile.duplicates.title": "Saropa Lints: Cross-File  ⁇  پیدا کردن بلوک های خطی تکراری",
  "command.crossFile.snapshot.title": "Saropa Lints: چند-فایلی — نوشتن اسنپ‌شات پروژه (JSON)",
  "command.crossFile.graph.title": "Saropa Lints: چند-فایلی — صدور نمودار واردات (DOT)",
  "command.crossFile.report.title": "Saropa Lints: Cross-File  ⁇  گزارش HTML را تولید می کند.",
  "command.openViolationsWideReport.title": "Saropa Lints: باز کردن داشبورد یافته ها",
  "command.openConsolidatedDashboard.title": "Saropa Lints: _PH0_: = PH0__::: -پای داشبورد را باز کنید Dashboard",
  "command.openViolationsWideReport.category": "Saropa",
  "command.revealFindingsDashboard.title": "Saropa Lints: باز کردن داشبورد یافته ها (فلترهای حفظ)",
  "command.focusView.title": "Saropa Lints: تمرکز بر نوار کناری Saropa Lints",
  "command.focusIssues.title": "Saropa Lints: نمایش تمام نقض ها",
  "command.focusIssuesForFile.title": "Saropa Lints: نقض پرونده ها را برای فایل نشان دهید",
  "command.openFileAndFocusIssues.title": "Saropa Lints: فایل را باز کنید و نقض ها را نشان دهید.",
  "command.focusIssuesForActiveFile.title": "Saropa Lints: در Saropa Lints نشان داده شود.",
  "command.focusIssuesWithImpactFilter.title": "Saropa Lints: نقض ها را بر اساس تاثیرات نشان دهید.",
  "command.focusIssuesWithSeverityFilter.title": "Saropa Lints: نقض ها را بر اساس شدت نشان دهید.",
  "command.focusPackageVibrancyPackages.title": "Saropa Lints: تمرکز بر درخت پویایی بسته",
  "command.refresh.title": "به راحتی و با آرامش استراحت کنید.",
  "command.repairConfig.title": "Saropa Lints: تعمیر گزینه‌های تحلیل",
  "command.setTier.title": "Saropa Lints: تنظیم سطح",
  "command.showOutput.title": "Saropa Lints: نمایش خروجی",
  "command.showRelatedRuleTelemetry.title": "Saropa Lints: نمایش تله‌متری قوانین مرتبط",
  "command.resetRelatedRuleTelemetry.title": "Saropa Lints: تنظیم مجدد کنترل از راه دور قواعد مرتبط",
  "command.copyLatestReport.title": "Saropa Lints: کپی آخرین گزارش",
  "command.openLatestReport.title": "Saropa Lints: آخرین گزارش باز",
  "command.setIssuesFilter.title": "فیلتر کردن بر اساس متن...",
  "command.setIssuesFilterByType.title": "فیلتر بر اساس شدت و تاثیر ...",
  "command.setIssuesFilterByRule.title": "فیلتر کردن بر اساس نام قانون ...",
  "command.setIssuesFilterByMetadata.title": "فیلتر کردن بر اساس قانون...ميتاداتا",
  "command.reviewHotspotState.title": "بررسی وضعیت نقاط امنیتی...",
  "command.clearIssuesFilters.title": "فیلترهای پاک را از بین ببرید.",
  "command.clearSuppressions.title": "سرکوب های آشکار",
  "command.hideFolder.title": "پوشه را از نمایش پنهان کنید",
  "command.hideFile.title": "فایل را از نمایش پنهان کنید",
  "command.hideRule.title": "قانون پنهان کردن از دید را مخفی کنید.",
  "command.hideRuleInFile.title": "قانون پنهان کردن در این فایل",
  "command.hideSeverity.title": "این شدت را پنهان کنید.",
  "command.hideImpact.title": "این ضربه را پنهان کنید",
  "command.copyPath.title": "مسیر کپی کردن را کپی کنید.",
  "command.copyMessage.title": "پیام را کپی کنید.",
  "command.toggleSidebarSection.title": "Saropa Lints: Toggle Activity Bar Section بخش نوار فعالیت را تغییر دهید.",
  "command.issues.copyAsJson.title": "Copy Violations به عنوان JSON کپی می شود.",
  "command.summary.copyAsJson.title": "خلاصه را به عنوان JSON کپی کنید.",
  "command.securityPosture.copyAsJson.title": "کپی کردن Security Posture به عنوان JSON",
  "command.fileRisk.copyAsJson.title": "کپی کردن فایل Risk به عنوان JSON",
  "command.fileRisk.showViolations.title": "Show Violations برای فایل ها",
  "command.fileRisk.hideFile.title": "فایل های مخفی شده را پنهان کنید",
  "command.fileRisk.copyPath.title": "کپی مسیر، کاپی مسیر",
  "command.explainRule.title": "توضیح قاعده قانون",
  "command.explainRuleFromSuggestion.title": "توضیح قاعده (از پیشنهاد)",
  "command.enableRule.title": "فعال کردن قاعده enable rule",
  "command.openFinding.title": "باز کردن یافته ی Open Finding",
  "command.applyFix.title": "Apply fix استفاده کنید",
  "command.fixAllInFile.title": "همه چیز را در این فایل درست کنید.",
  "command.focusFile.title": "فقط این فایل را نشان دهید",
  "command.clearFocusFile.title": "نمایش تمام فایل ها را نشان دهید",
  "command.toggleInlineAnnotations.title": "Saropa Lints: Toggle Inline Annotations (تغییر دادن توضیحات خطی در متن)",
  "command.focusIssuesForRules.title": "نشان دادن نقض در موارد زیر",
  "command.focusIssuesByRuleMetadata.title": "تمرکز بر نقض قوانین توسط Metadata Rule",
  "command.focusIssuesForOwasp.title": "نقض تمرکز برای دسته OWASP",
  "command.disableRules.title": "قاعده غیرفعال کردن (deactivate rule)",
  "command.enableRules.title": "قوانین فعال کردن (Enable rule)",
  "command.exportOwaspReport.title": "Saropa Lints: صدور گزارش انطباق OWASP",
  "command.setGroupBy.title": "گروه بندی به ...",
  "command.openWalkthrough.title": "Saropa Lints: شروع کردن کار",
  "command.showAbout.title": "درباره Saropa Lints",
  "command.openHelpHub.title": "Saropa Lints: کمک به کمک",
  "command.openPubDevSaropaLints.title": "Saropa Lints: بسته را در pub.dev باز کنید.",
  "command.createSaropaInstructions.title": "ایجاد Saropa Lints دستورالعمل برای عوامل هوش مصنوعی",
  "command.packageVibrancy.scan.title": "بسته های اسکن Scan Packages",
  "command.packageVibrancy.rescan.title": "بسته های Rescan (تازه)",
  "command.packageVibrancy.openOtherProject.title": "اسکن پروژه دیگری...",
  "command.packageVibrancy.showReport.title": "داشبورد بسته را باز کنید",
  "command.packageVibrancy.focus.title": "بسته ی Vibrancy: داشبورد باز (کمپکت)",
  "command.packageVibrancy.clearCache.title": "پاک کردن کش (Cache)",
  "command.packageVibrancy.exportReport.title": "گزارش صادرات: گزارش صادراتی",
  "command.packageVibrancy.browseKnownIssues.title": "مرور مسائل شناخته شده",
  "command.packageVibrancy.exportSbom.title": "صادرات SBOMOM صدور",
  "command.packageVibrancy.annotatePubspec.title": "وابستگی ها را یادداشت کنید",
  "command.packageVibrancy.goToPackage.title": "به pubspec.yaml بروید.",
  "command.packageVibrancy.goToLine.title": "به خط pubspec.yaml بروید.",
  "command.packageVibrancy.openOnPubDev.title": "در pub.dev باز می شود.",
  "command.packageVibrancy.showChangelog.title": "در pub.dev Changelog را باز کنید.",
  "command.packageVibrancy.updateToLatest.title": "به روز رسانی جدیدترین نسخه",
  "command.packageVibrancy.copyAsJson.title": "کپی کردن به عنوان JSON",
  "command.packageVibrancy.upgradeAndTest.title": "ارتقاء و تست کردن & Test",
  "command.packageVibrancy.suppressPackage.title": "Suppress Package بسته ای را سرکوب کنید",
  "command.packageVibrancy.unsuppressPackage.title": "بسته Unsuppress را باز کنید",
  "command.packageVibrancy.openUrl.title": "لینک باز کنید Open Link",
  "command.packageVibrancy.openSourceFolder.title": "پوشه منبع باز Open Source Folder",
  "command.packageVibrancy.commentOutUnused.title": "Comment Out وابستگی های استفاده نشده",
  "command.packageVibrancy.deleteUnused.title": "حذف وابستگی های استفاده نشده (با پشتیبان گیری)",
  "command.packageVibrancy.planUpgrades.title": "برنامه ریزی و اجرای ارتقاء ها",
  "command.packageVibrancy.goToOverride.title": "به بخش Override Dependency بروید و آن را رد کنید.",
  "command.packageVibrancy.suppressPackageByName.title": "توقف هشدارهای تشخیصی بسته",
  "command.packageVibrancy.suppressByCategory.title": "سرکوب کردن بر اساس دسته بندی...",
  "command.packageVibrancy.suppressAllProblems.title": "تمام بسته های ناسالم را سرکوب کنید",
  "command.packageVibrancy.unsuppressAll.title": "باز کردن حذف تمام بسته ها",
  "command.packageVibrancy.sortDependencies.title": "وابستگی ها را به ترتیب الفبایی مرتب کنید",
  "command.packageVibrancy.showCodeLens.title": "نشان دادن نشان های زندگی پر جنب و جوش",
  "command.packageVibrancy.hideCodeLens.title": "پنهان کردن نشان های پر جنب و جوش",
  "command.packageVibrancy.toggleCodeLens.title": "نشان های Toggle Badges را تغییر دهید",
  "command.packageVibrancy.focusDetails.title": "جزئیات بسته فوکوس (Focus Package)",
  "command.packageVibrancy.logDetails.title": "ورود به خروجی برای خروجي",
  "command.packageVibrancy.logAllDetails.title": "Log همه جزئیات بسته بندی",
  "command.packageVibrancy.updateFromCodeLens.title": "به روز رسانی نسخه بسته بندی Update Package Version",
  "command.packageVibrancy.focusPackageInTree.title": "بسته نمایش در Tree View را نشان دهید",
  "command.packageVibrancy.updateAllLatest.title": "به روز رسانی تمام وابستگی ها (تازه ترین)",
  "command.packageVibrancy.updateAllMajor.title": "به روز رسانی تمام وابستگی ها (فقط عمده)",
  "command.packageVibrancy.updateAllMinor.title": "به روز رسانی تمام وابستگی ها (فقط جزئی)",
  "command.packageVibrancy.updateAllPatch.title": "به روز رسانی تمام وابستگی ها (تنها تکه)",
  "command.packageVibrancy.showPrereleases.title": "نمایش نسخه های پیش انتشار را نشان دهید",
  "command.packageVibrancy.hidePrereleases.title": "نسخه های پیش انتشار را پنهان کنید",
  "command.packageVibrancy.updateToPrerelease.title": "به روز رسانی برای پیش انتشار",
  "command.packageVibrancy.generateCiConfig.title": "تولید خط لوله CI Pipeline",
  "command.packageVibrancy.addRegistryAuth.title": "اضافه کردن احراز هویت رجیستری",
  "command.packageVibrancy.removeRegistryAuth.title": "حذف احراز هویت رجیستری (Registry Authentication)",
  "command.packageVibrancy.listRegistries.title": "لیست ثبت نامهای پیکربندی شده را فهرست کنید.",
  "command.packageVibrancy.comparePackages.title": "مقایسه بسته های خرید",
  "command.packageVibrancy.compareSelected.title": "مقایسه بسته های انتخاب شده با هم",
  "command.packageVibrancy.copyHoverToClipboard.title": "کپی اطلاعات بسته بندی",
  "command.packageVibrancy.showPackagePanel.title": "جزئیات بسته را نشان دهید",
  "command.packageVibrancy.search.title": "جستجو Search جستجوی جستجو",
  "command.packageVibrancy.filterBySeverity.title": "فیلتر بر اساس شدت...",
  "command.packageVibrancy.filterByProblemType.title": "فیلتر بر اساس نوع مشکل...",
  "command.packageVibrancy.filterByCategory.title": "فیلتر بر اساس سلامت...",
  "command.packageVibrancy.filterBySection.title": "فیلتر بر اساس بخش ...",
  "command.packageVibrancy.showProblemsOnly.title": "فقط مشکلات را نشان دهید",
  "command.packageVibrancy.clearFilters.title": "فیلترهای پاک را تمیز کنید",
  "command.packageVibrancy.expandAll.title": "همه را گسترش دهید Expand All",
  "command.todosAndHacks.refresh.title": "TODOs & Hacks: بروزرسانی",
  "command.todosAndHacks.toggleGroupByTag.title": "TODOs & Hacks: گروه بندی با برچسب / پوشه را تغییر دهید.",
  "command.todosAndHacks.enableWorkspaceScan.title": "TODOs & Hacks: امکان اسکن فضای کاری را فعال کنید.",
  "command.driftAdvisor.refresh.title": "مشاور انحراف: بروزرسانی",
  "command.driftAdvisor.openInBrowser.title": "Drift Advisor: در مرورگر باز می شود.",
  "command.driftAdvisor.enableIntegration.title": "Drift Advisor: امکان ادغام را فراهم می کند",
  "command.driftAdvisor.disableIntegration.title": "Drift Advisor: غیرفعال کردن ادغام",
  "command.showCommandCatalog.title": "Saropa Lints: مرور تمام فرمان ها",
  "config.property.enabled.markdownDescription": "هنگامی که **on** (پیش فرض) ، Saropa Lints چک های ارتقاء را اجرا می کند و فضای کاری را به عنوان استفاده از یکپارچه سازی lint Saropa درمان می کند. **Saropa Lints را خاموش کنید تا بدون پنهان کردن گزینه های نوار جانبی، اعلانات ادغام و نمره بار وضعیت را متوقف کند. **__ PH3__: پروژه تنظیم کنید** زمانی که شما نیاز به اضافه کردن `saropa_lints⌒ به pubspec دارید و نوشتن ゙analysis_options⌒ می کنید.",
  "config.property.tier.description": "سطح پیش فرض هنگام فعال کردن یا دوباره شروع کار.",
  "config.property.runAnalysisAfterConfigChange.description": "dart analyze را پس از init یا config change اجرا کنید.",
  "config.property.runAnalysisAfterDependencyChange.description": "dart analyze را به طور خودکار دوباره اجرا کنید وقتی که تغییراتی در pubspec.lock ایجاد شود (بعد از pub get / pub upgrade). از یک زمان ۱۰ ثانیه ای برای حل سریع وابستگی ها استفاده می کند.",
  "config.property.uiLanguage.description": "زبان رابط کاربری برای Saropa sidebar و داشبورد. از \"auto\" برای دنبال کردن زبان نمایش VS Code استفاده کنید. انتخاب کننده زبان در نوار کناری این مقدار را به تنظیمات کاربر ذخیره می کند، بنابراین در هر فضای کاری اعمال می شود.",
  "config.property.runAnalysisOpenEditorsOnly.description": "وقتی درست است، Saropa Lints dart analyze را فقط برای فایل‌های Dart اجرا می‌کند که در حال حاضر در VS Code (workspace.textDocuments) زیر ریشه پروژه شناسایی‌شده باز هستند.",
  "config.property.regressionNudge.enabled.markdownDescription": "هنگامی که **در** (پیش فرض) ، نشان دادن یک بار به هر زمان امتیاز سلامت عبور زیر لبه باند (90, 80, 70, 60, 50). یادآوری برای یک باند داده شده تنها پس از بازیابی امتیاز به وضوح بالاتر از آن گروه، دوباره باز می شود، بنابراین نمره ای که در اطراف لبه نوسان دارد دیگر پاپ آپ های تکراری تولید نمی کند. **off** را خاموش کنید تا تمام نخ های رگرسیونی کاملاً ساکت شوند در حالی که همه رفتارهای دیگر Saropa Lints حفظ می شود.",
  "config.property.upgradePackNudge.enabled.markdownDescription": "وقتی **در** (پیش فرض) ، یک بار در هر فضای کاری برای فعال کردن یک بسته قواعد مهاجرت semver-gated (به عنوان مثال Dio 5.x، بلوک 8.x، Riverpod 2.x/3.x, , ریورپود 2 go_router 6.x) زمانی که نسخه ی حل شده `pubspec.lock` با دروازه بسته مطابقت دارد اما این بسته فعال نیست. این پیشنهاد پس از یک ارتقاء عمومی که بسته جدیدی را به محدوده می آورد، دوباره ظاهر می شود. **off** را برای خاموش کردن این پیشنهادات بسته ارتقاء، روشن کنید.",
  "config.property.inlineAnnotations.description": "پیام های نقض را در انتهای خطوط تحت تاثیر قرار گرفته نشان دهید (اسلوب غلط لنز).",
  "config.property.issuesPageSize.description": "حداکثر تعداد تخلفات نشان داده شده در هر پرونده در یافته های گروه بندی (Findings Dashboard / لیست داخلی). باقی مانده به عنوان \"و N بیشتر ...\" نشان داده شده است.",
  "config.property.violationsGroupBy.description": "گروه بندی پیش فرض برای یافته های لنت (Findings Dashboard / لیست گروهی). \"تاثیر\" لیست های مهم و بالا را در ابتدا قرار می دهد؛ برای تغییر موقت از نوار ابزار داشبورد استفاده کنید.",
  "config.property.checkForUpdates.description": "به طور دوره ای نسخه های جدیدتر بسته saropa_lints را بررسی کنید و پیشنهاد ارتقاء دهید.",
  "config.property.pubspecValidation.preferPinnedVersions.markdownDescription": "هنگامی که **on**، اعتبار سنجی pubspec ترجیح می دهد نسخه دقیق پین (`1.2.3') و پرچم های محدوده caret (`^1.2.3) را داشته باشد. وقتی **off** (پیش فرض) باشد، سنتکس caret را ترجیح می دهد و نسخه های خالی را نشان می دهد که با رفتار adddart pub مطابقت دارد. در هر زمان فقط یک حالت فعال است.",
  "config.section.Code.Health.title": "کد سلامت بهداشت و درمان",
  "config.property.projectVibrancy.lcovPath.markdownDescription": "مسیر فایل LCOV برای اسکن های **Code Health** از داشبورد (نسبت به ریشه پروژه یا مطلق). همان طور که CLI `--lcov̅  ⁇  اینجا را پیکربندی می کند تا هرگز به اجرای تنها CLI اعتماد نکنید. کلید تنظیمات به عنوان `projectVibrancy.*∀ نگه داشته می شود، بنابراین تنظیمات کاربر موجود پس از تغییر نام داشبورد از Project Vibrance کار خود را ادامه می دهد.",
  "config.property.projectVibrancy.minGrade.description": "حداقل نمره متوسط (A=بهترین). F این دروازه را برای اسکن های تمدید غیرفعال می کند. شکست های دروازه غیر صفر هنوز هم یک بنر و JSON قابل کپی را نشان می دهد.",
  "config.property.projectVibrancy.maxUnused.markdownDescription": "وقتی تعداد تابع های استفاده نشده از این مقدار بیشتر شود، اسکن را ناکام می کند. **0** = این گیت را اعمال نکنید (همان طور که حذف `--max-unused`).",
  "config.property.projectVibrancy.maxUncovered.markdownDescription": "وقتی تعداد تابع های کشف شده از این مقدار بیشتر شود، خطا می کند. **0** = off .",
  "config.property.projectVibrancy.maxStubTested.markdownDescription": "وقتی تعداد تابع تست شده از این مقدار بیشتر شود، خطا می کند. **0** = off .",
  "config.property.projectVibrancy.maxSuspiciousCoverage.markdownDescription": "وقتی تعداد تابع ̋مشتبه_تغطیه› از این مقدار فراتر رود، خطا می کند. **0** = off.",
  "config.property.projectVibrancy.maxTestDrift.markdownDescription": "وقتی که `test_drift̅ count تابع از این مقدار فراتر رود، ناکام می شود. **0** = off.",
  "config.section.Activity.bar.title": "نوار فعالیت (Activity Bar) ، یک بار است.",
  "config.property.sidebar.showOverview.description": "**Saropa Lints** نوار کناری را نمایش دهید (لیست صاف از داشبورد های ویرایشگر، اقدامات، ردیف های وضعیت، تنظیمات، طبقه بندی و لینک های کمک). خلاصه مفصل، ریسک فایل، پکیج Vibrancy و داشبورد های Drift در برگه های ویرایشگر زندگی می کنند.",
  "config.section.TODOs.Hacks.title": "TODOs & Hacks ها و هک های جدید",
  "config.property.todosAndHacks.workspaceScanEnabled.description": "اجازه دهید TODOs & Hacks فضای کاری را برای نشانگرهای نظر (TODO، FIXME، ...) اسکن کند. فضای کاری اسکن بسیاری از فایل ها را فعال می کند - قابل اعتماد است وقتی به بخش TODO صفحه نمایش یافته های تخته راهنما متکی هستید.",
  "config.property.todosAndHacks.tags.description": "برچسب هایی که در نظرات جستجو می شوند (in regex حساس به مورد).",
  "config.property.todosAndHacks.includeGlobs.description": "الگوهای Glob برای فایل هایی که باید اسکن شوند (به طور پیش فرض کد و config). اضافه کردن **/*.md برای شامل شدن Markdown docs.",
  "config.property.todosAndHacks.excludeGlobs.description": "الگوهای استثنایی اضافی (با search.exclude ادغام شده است).",
  "config.property.todosAndHacks.maxFilesToScan.description": "حداکثر تعداد فایل هایی که باید اسکن شوند؛ نمایش یک پیام را هنگام کپی کردن نشان می دهد.",
  "config.property.todosAndHacks.autoRefresh.description": "هنگام ذخیره (debounced) یک فایل، نمایش TODOs & Hacks را تازه کنید.",
  "config.property.todosAndHacks.groupByTag.description": "درخت گروه بندی را بر اساس برچسب (TODO، FIXME ...) و سپس فایل؛ هنگامی که خاموش است، به صورت پوشه ای و سپس پرونده.",
  "config.property.todosAndHacks.customRegex.description": "گزینه اختیاری برای رد کردن regex برای نشانگرهای تعریفی مطابقت. بر اساس خط؛ از گروه 1 برای برچسب و گروه 2 اختیاری برای قطعه استفاده کنید. خالی = از پیش فرض استفاده کنید (//, #, <!-- + برچسب ها). Regex نامعتبر به حالت پیش فرض باز می گردد.",
  "config.section.Drift.Advisor.title": "Drift Advisor",
  "config.property.driftAdvisor.integration.description": "امکان ادغام اختیاری با Saropa Drift Advisor را فعال کنید. هنگامی که روشن است، این افزونه یک سرور در حال اجرا Drift Advisor (پورت 8642 ⁇ 8649) را کشف می کند، پیشنهادات و ناهنجاری های شاخص را دریافت می کند و آنها را در نمای مشاور Drift و به صورت اختیاری در مشکلات نشان می دهد.",
  "config.property.driftAdvisor.hosts.description": "میزبان ها برای اسکن سرور Drift Advisor، به ترتیب امتحان شده اند. پیش فرض به [127.0.0.1\"] (localhost) است. اضافه کردن IP های LAN (به عنوان مثال \"192.168.1.151\") برای رسیدن به سرورهای خارج از جعبه، مانند تلفن هایی که با Wi-Fi متصل هستند. هر ورودی در سراسر محدوده پورت بالا اسکن می شود؛ یک پورت دقیق را با \"host:port\" پین کنید (به عنوان مثال \"192.168.1.151:9000\") تا فقط آن نقطه نهایی را بررسی کند.",
  "config.property.driftAdvisor.portRange.description": "محدوده پورت [min, max] برای اسکن سرور Drift Advisor (شامل)",
  "config.property.driftAdvisor.pollIntervalMs.description": "چند بار باید سرور Drift Advisor را برای مشکلات (میلی ثانیه) بررسی کرد. برای غیرفعال کردن رای گیری خودکار (تجدید دستی) ، آن را به صفر تنظیم کنید.",
  "config.property.driftAdvisor.showInProblems.description": "انتشار مسائل در مورد Drift Advisor به عنوان تشخیصی در نمایش مشکلات (منبع: Saropa مشاور جریان).",
  "config.section.Package.Vibrancy.title": "بسته بندی Vibrancy",
  "config.property.packageVibrancy.githubToken.description": "GitHub توکن دسترسی شخصی برای افزایش محدودیت نرخ API (60 / ساعت بدون، 5000 / ساعت با)",
  "config.property.packageVibrancy.scanOnOpen.description": "به طور خودکار اسکن زمانی که یک پروژه Flutter باز می شود.",
  "config.property.packageVibrancy.autoExportReportsOnScan.description": "به طور خودکار پس از هر اسکن موفق، گزارش های Markdown و JSON را ذخیره کنید.",
  "config.property.packageVibrancy.includeDevDependencies.description": "dev_dependencies را در اسکن ویبرانیتی وارد کنید.",
  "config.property.packageVibrancy.includeOverriddenPackages.description": "شامل dependence_overrides (path/git) در اسکن ویبرانیتی برای بررسی های امنیتی و بهداشتی می شود.",
  "config.property.packageVibrancy.cacheTtlHours.description": "TTL حافظه ی کش در ساعت برای پاسخ های API",
  "config.property.packageVibrancy.startupScanSkipTtlMinutes.description": "اسکن پرانرژی راه اندازی را نادیده بگیرید اگر آخرین اسکن کامل شده در این چند دقیقه تمام شود و pubspec.lock + config scan بدون تغییر باشد. برای همیشه اجرای اسکن استارت آپ (بدون پرش) ، آن را به 0 تنظیم کنید.",
  "config.property.packageVibrancy.showStartupScanSkipStatusBar.description": "هنگامی که اسکن راه اندازی (اسکین) حذف می شود (نتایج ذخیره شده دوباره استفاده می شوند) ، یک شاخص بار وضعیت کوتاه را نشان دهید. برای سکوت بی تنظیم بگذارید.ریدراته کنید.",
  "config.property.packageVibrancy.suppressedPackages.description": "نام بسته برای سرکوب از تشخیصی های پر جنب و جوش و هور (هنوز اسکن شده، در درخت کم نور نشان داده می شود)",
  "config.property.packageVibrancy.allowlist.description": "نام بسته هایی که در طول اسکن وایبرنسی (به عنوان مثال، بسته های داخلی) حذف می شوند.",
  "config.property.packageVibrancy.repoOverrides.description": "GitHub URL های مخزن را برای بسته هایی که داده های pub.dev در آن اشتباه است، رد کنید.",
  "config.property.packageVibrancy.siblingRepoPaths.description": "مسیرهای سیستم فایل به repo های خواهر و برادر. وابستگی های pubspec آنها با این پروژه مقایسه می شود تا چرخش نسخه بین پروژه ها را نشان دهد (همین بسته در جای دیگر به یک رشته مختلف متصل شده است).",
  "config.property.packageVibrancy.registries.description": "پیکربندی رجیستری برای سرورهای خصوصی Pub. توکن ها به طور ایمن در VS Code ذخیره سازی مخفی نگهداری می شوند.",
  "config.property.packageVibrancy.showLockDiffNotifications.description": "یک اطلاعیه خلاصه ای از تغییرات فایل قفل را پس از هر اسکن، نشان دهید.",
  "config.property.packageVibrancy.showInStatusBar.description": "نمره ی زندگی بسته را در کنار نمره سلامت لنت در نوار وضعیت نشان دهید.",
  "config.property.packageVibrancy.enableCodeLens.description": "نشان دادن برچسب های نمره ی زنده بودن به عنوان توضیحات CodeLens بالای هر وابستگی در pubspec.yaml",
  "config.property.packageVibrancy.enableAdoptionGate.description": "نشان دادن برچسب های زنده سازی برای بسته های جدید که به pubspec.yaml اضافه شده اند.",
  "config.property.packageVibrancy.codeLensDetail.description": "کنترل می کند که چقدر جزئیات در توضیحات CodeLens نشان داده شده است.",
  "config.property.packageVibrancy.codeLensDetail.enumDescription.1": "فقط نمره و دسته بندی",
  "config.property.packageVibrancy.codeLensDetail.enumDescription.2": "نمره، دسته بندی و وضعیت به روز رسانی",
  "config.property.packageVibrancy.codeLensDetail.enumDescription.3": "امتیاز، دسته بندی، اندازه آرشیو، وضعیت به روز رسانی و هشدارها",
  "config.property.packageVibrancy.indicators.description": "نمادهای سفارشی برای شاخص های وضعیت.",
  "config.property.packageVibrancy.indicatorStyle.description": "چگونه شاخص های وضعیت را در CodeLens نمایش دهیم",
  "config.property.packageVibrancy.indicatorStyle.enumDescription.1": "فقط ایموجی را نشان دهید",
  "config.property.packageVibrancy.indicatorStyle.enumDescription.2": "فقط متن را نشان دهید (Vibrant)",
  "config.property.packageVibrancy.indicatorStyle.enumDescription.3": "هر دو را نشان دهید (ایموجی + متن)",
  "config.property.packageVibrancy.indicatorStyle.enumDescription.4": "فقط نمره را نشان می دهد، هیچ شاخصی وجود ندارد.",
  "config.property.packageVibrancy.sortSdkFirst.description": "وابستگی های SDK (flutter, flutter_test) را در بالای صفحه هنگام مرتب سازی نگه دارید.",
  "config.property.packageVibrancy.endOfLifeDiagnostics.description": "چگونه تشخیص بسته های پایان عمر را در ویرایشگر نمایش دهیم؟",
  "config.property.packageVibrancy.endOfLifeDiagnostics.enumDescription.1": "هیچ تشخیصی برای بسته های پایان عمر (تنها در نوار کناری مشاهده می شود)",
  "config.property.packageVibrancy.endOfLifeDiagnostics.enumDescription.2": "نشان دادن به عنوان اشاره (زیرخط ظریف)",
  "config.property.packageVibrancy.endOfLifeDiagnostics.enumDescription.3": "فقط زمانی که یک جایگزین شناخته شده است، به عنوان هشدار نشان دهید، در غیر این صورت Hint اشاره می کند.",
  "config.property.packageVibrancy.inlineDiagnostics.description": "چند مورد از مسائل Package Vibrancy به عنوان تشخیص های خطی در pubspec.yaml نمایش داده می شود.",
  "config.property.packageVibrancy.inlineDiagnostics.enumDescription.1": "فقط مسائل مهم را در خط قرار دهید: پایان زندگی، آسیب پذیری ها، منازعات خانوادگی (توصیه شده)",
  "config.property.packageVibrancy.inlineDiagnostics.enumDescription.2": "یک تشخیصی در هر بسته (در پب های بزرگ می تواند سر و صدا داشته باشد)",
  "config.property.packageVibrancy.inlineDiagnostics.enumDescription.3": "بدون تشخیص های داخلی  ⁇  از گزارش ویرایشگر بسته Vibrancy استفاده کنید.",
  "config.property.packageVibrancy.weights.resolutionVelocity.description": "وزن برای سرعت رزولوشن در V_score (پیش فرض 0.5)",
  "config.property.packageVibrancy.weights.engagementLevel.description": "وزن برای سطح تعامل در V_score (تعیین شده 0.4)",
  "config.property.packageVibrancy.weights.popularity.description": "وزن محبوبیت در V_score (پیش فرض 0.1)",
  "config.property.packageVibrancy.publisherTrustBonus.description": "حداکثر پاداش زمانی که ناشر pub.dev وابستگی در لیست قابل اعتماد (dart.dev، google.dev ، flutter.dev و firebase.google.com) باشد .",
  "config.property.packageVibrancy.upgradeAutoCommit.description": "خودکار کردن هر مرحله ارتقاء موفق (تولید یک commit در هر بسته)",
  "config.property.packageVibrancy.upgradeSkipTests.description": "درهای تست پرش فلاتر را هنگام اجرای ارتقاء (سریع تر اما کمتر ایمن) رد کنید.",
  "config.property.packageVibrancy.upgradeMaxSteps.description": "حداکثر تعداد مراحل ارتقاء برای اجرای در یک اجرا",
  "config.property.packageVibrancy.bulkUpdateConfirmation.description": "نمایش دیالوگ تایید قبل از بروز رسانی انبوه وابستگی ها",
  "config.property.packageVibrancy.watchEnabled.description": "امکان بررسی پس زمینه برای نسخه های جدید بسته را فراهم کنید.",
  "config.property.packageVibrancy.watchIntervalHours.description": "چند بار باید نسخه های جدید بسته را بررسی کرد (در ساعت)",
  "config.property.packageVibrancy.watchFilter.description": "فیلتر که بسته ها را برای مشاهده نسخه های جدید به دنبال آن هستند.",
  "config.property.packageVibrancy.watchFilter.enumDescription.1": "تمام وابستگی های مستقیم را تماشا کنید.",
  "config.property.packageVibrancy.watchFilter.enumDescription.2": "فقط بسته های ساعت با نمره ی جان بخشی زیر ۴۰ را انتخاب کنید.",
  "config.property.packageVibrancy.watchFilter.enumDescription.3": "فقط ساعت های بسته بندی شده که در watchList مشخص شده اند.",
  "config.property.packageVibrancy.watchList.description": "نام بسته هایی که باید برای نسخه های جدید مورد توجه قرار گیرند (فقط زمانی استفاده می شود که watchFilter \"تخصیص\" باشد).",
  "config.property.packageVibrancy.annotateSectionHeaders.description": "عنوان های بخش تزئینی را بالای بخش های اصلی pubspec قرار دهید.",
  "config.property.packageVibrancy.treeGrouping.description": "چگونه بسته ها را در نمای درخت گروه بندی کنیم",
  "config.property.packageVibrancy.treeGrouping.enumDescription.1": "لیست مسطح مرتب شده بر اساس نمره ی پر جنب و جوش (بدترین ها اول)",
  "config.property.packageVibrancy.treeGrouping.enumDescription.2": "گروه بندی بر اساس بخش pubspec (تکمیل ها، dev_dependencies)",
  "config.property.packageVibrancy.showPrereleases.description": "نمایش نسخه های پیش از انتشار (dev، beta، rc) در CodeLens و tree view",
  "config.property.packageVibrancy.prereleaseTagFilter.description": "فقط نسخه های پیش از انتشار را که با این برچسب ها مطابقت دارند نشان دهید (به عنوان مثال ['beta', 'rc']). خالی = همه را نشان دهید.",
  "config.property.packageVibrancy.onSaveChanges.description": "دستور اجرا در هنگام ذخیره pubspec.yaml با تغییرات وابستگی. خالی = غیرفعال.",
  "config.property.packageVibrancy.onSaveChangesDetection.description": "چه زمانی باید کار بر روی ذخیره کردن وظیفه را فعال کرد.",
  "config.property.packageVibrancy.onSaveChangesDetection.enumDescription.1": "هر pubspec.yaml ذخیره شده ای را اجرا کنید.",
  "config.property.packageVibrancy.onSaveChangesDetection.enumDescription.2": "فقط زمانی اجرا شود که بخش های وابستگی تغییر کنند.",
  "config.property.packageVibrancy.budget.maxDependencies.description": "حداکثر تعداد وابستگی های کل مجاز (null = بدون محدودیت)",
  "config.property.packageVibrancy.budget.maxTotalSizeMB.description": "حداکثر اندازه کل آرشیو در مگابایت (null = بدون محدودیت)",
  "config.property.packageVibrancy.budget.minAverageVibrancy.description": "حداقل نمره متوسط حیات مورد نیاز در تمام وابستگی ها (صفر = بدون محدودیت)",
  "config.property.packageVibrancy.budget.maxAbandoned.description": "حداکثر تعداد بسته های رها شده مجاز (null = بدون محدودیت)",
  "config.property.packageVibrancy.budget.maxEndOfLife.description": "حداکثر تعداد بسته های پایان عمر مجاز (null = بدون محدودیت)",
  "config.property.packageVibrancy.budget.maxOutdated.description": "حداکثر تعداد بسته های منسوخی مجاز (null = بدون محدودیت)",
  "config.property.packageVibrancy.budget.maxUnused.description": "حداکثر تعداد وابستگی های استفاده نشده مجاز (null = بدون محدودیت)",
  "config.property.packageVibrancy.enableVulnScan.description": "پرس و جو OSV پایگاه داده برای آسیب پذیری های شناخته شده در وابستگی ها.",
  "config.property.packageVibrancy.enableGitHubAdvisory.description": "پرس و جو GitHub پایگاه داده مشاوره ای برای توصیه های امنیتی اضافی.",
  "config.property.packageVibrancy.enableVersionGap.description": "گرفتن روابط عمومی و مسائل بین نسخه فعلی خود را و آخرین از GitHub. برای بهترین نتایج، نیاز به یک توکن GitHub دارد.",
  "config.property.packageVibrancy.vulnSeverityThreshold.description": "حداقل سطح شدت برای نمایش تشخیص آسیب پذیری",
  "config.property.packageVibrancy.vulnSeverityThreshold.enumDescription.1": "تنها آسیب پذیری های بحرانی (CVSS 9.0+) را نشان می دهد.",
  "config.property.packageVibrancy.vulnSeverityThreshold.enumDescription.2": "نشان دادن آسیب پذیری های مهم و جدی (CVSS 7.0+)",
  "config.property.packageVibrancy.vulnSeverityThreshold.enumDescription.3": "نمایش متوسط، بالا و بحرانی (CVSS 4.0+)",
  "config.property.packageVibrancy.vulnSeverityThreshold.enumDescription.4": "نمایش تمام آسیب پذیری ها",
  "walkthrough.gettingStarted.title": "شروع کار با Saropa Lints",
  "walkthrough.gettingStarted.description": "Health Score، Findings dashboard، security matrix، triage و trends  ⁇  نوار فعالیت به علاوه تب های full-width editor.",
  "walkthrough.step.walkthrough.healthScore.title": "نمره سلامت Health Score به صورت زیر است:",
  "walkthrough.step.walkthrough.healthScore.description": "کیفیت پروژه شما در یک نگاه: **0 ⁇ 100 امتیاز** در نوار وضعیت و نمای کلی.\n\nسبز (80+) ، زرد (50 ⁇ 79), قرمز (<50). اشتباهات به شدت جریمه می شوند. [Run analysis] ((کمان:saropaLints.runAnalysis) · [Set up project} (کمان::saropa Lints.enable)",
  "walkthrough.step.walkthrough.issues.title": "نقض قوانین و توضیحات داخلی",
  "walkthrough.step.walkthrough.issues.description": "یافته ها در تاب ویرایشگر **دشبوردهای یافته ها**، گروه بندی شده بر اساس شدت و فایل. **توضیحات به سبک غلط لنز** هشدارها را در پایان هر سطر نشان می دهد.\n\nفیلتر کردن بر اساس متن، شدت، تاثیر یا قاعده. برای سرکوب نویز، روی راست کلیک کنید. [Run Analysis] ((کمان:saropaLints.runAnalysis))",
  "walkthrough.step.walkthrough.security.title": "وضعیت امنیتی: امنیت در موقعیت های امنیتی",
  "walkthrough.step.walkthrough.security.description": "**OWASP ماتریس پوشش 10 برتر**  ⁇  موبایل و وب. هر دسته بندی نشان دهنده نقض و تعداد قوانین است. برای فیلتر کردن نقض ها کلیک کنید.\n\nصادرات یک گزارش انطباق برای حسابرسی ها. [رپورتی برآمد OWASP]",
  "walkthrough.step.walkthrough.triage.title": "تریاژ (Triage) ، تعیین نوع بیماری است.",
  "walkthrough.step.walkthrough.triage.description": "قوانین گروه بندی شده بر اساس اولویت  ⁇ اشتباهات، باند های حجم و سبک. هر گروه **تأثیر برآورد شده نمره** را نشان می دهد.\n\nاز **Manage Rule Packs** برای فعال یا غیرفعال کردن قوانین و بسته های قواعد استفاده کنید؛ تغییرات را به YAML می نویسند و تجزیه و تحلیل را دوباره اجرا می کنند.\n\n[پاکت های قاعده را باز کنید و مدیریت کنید] ((کمان:saropaLints.openConfigDashboard))",
  "walkthrough.step.walkthrough.trends.title": "ریسک فایل و روند آن",
  "walkthrough.step.walkthrough.trends.description": "** ریسک فایل ها** پرونده ها را بر اساس تراکم نقض رتبه بندی می کند  ⁇  خطرناک ترین در اول.\n\nپنل وضعیت نشان دهنده پیشرفت نمره در طول زمان است. هشدارهای برگشت و جشن های مهم شما را در مسیر درست نگه می دارد.",
  "walkthrough.step.walkthrough.packageVibrancy.title": "بسته سلامت و سلامتی",
  "walkthrough.step.walkthrough.packageVibrancy.description": "وابستگی ها را برای شکاف های نسخه، سیگنال های تعمیر و نگهداری و مشکلات شناخته شده اسکن کنید. یک **CycloneDX SBOM** برای حسابرسی زنجیره تامین صادر کنید.\n\nنتایج به عنوان نشان های CodeLens و در تاب ویرایشگر **Package Dashboard** ظاهر می شوند.",
  "walkthrough.step.walkthrough.todosAndHacks.description": "هر نظر ∀TODO`, ▽HACK` و △FIXME̅ را در سراسر فضای کاری پیدا کنید. گروه بندی بر اساس نوع تگ یا پوشه و کلیک کنید تا به منبع بروید. [Refresh TODOs & Hacks] ((کمان:saropaLints.todosAndHacks.refresh)",
  "walkthrough.step.walkthrough.crossFile.title": "تجزیه و تحلیل پرونده های متقابل",
  "walkthrough.step.walkthrough.crossFile.description": "چک های پروژه را اجرا کنید که تجزیه و تحلیل یک فایل نمی تواند انجام دهد: پرونده های استفاده نشده، وابستگی های دایره ای، آمار واردات، وابستگی ویژگی ها، واردات مرده، نمادهای استفاده نشده ، کلید l10n استفاده نشده, بلوک های تکراری، عکس فوری JSON، صادرات نمودار و گزارش HTML.\n\n[فایل های استفاده نشده را پیدا کنید] (فرمان:saropaLints.crossFile.unusedFiles) · [تولید گزارش HTML Cross-File] (پردازش فایل های مورد نیاز برای ایجاد یک گزارش cross-file)",
  "walkthrough.step.walkthrough.commandCatalog.title": "مرور تمام دستورات فرماندهی",
  "walkthrough.step.walkthrough.commandCatalog.description": "بیش از 115 فرمان که بر اساس دسته بندی با جستجو سازماندهی شده اند. پیدا کردن تجزیه و تحلیل، امنیت، سلامت بسته ها و دستورات گزارش در یک مکان. [بروی همه فرمانها]",
  "walkthrough.step.walkthrough.aboutSaropa.title": "درباره Saropa",
  "walkthrough.step.walkthrough.aboutSaropa.description": "Saropa Pty Limited  ⁇  از سال 2010، در حال ساخت محافظهای دیجیتال است. Dart بسته ها، VS Code افزونه ها و برنامه های مصرفی برای توسعه دهندگان که به قابلیت اطمینان ارزش می دهند. [Visit saropa.com]",
  "command.toggleTodosAndHacksScanner.title": "Saropa Lints: Toggle TODO/HACK اسکنر فضای کاری"
}
